mcl_python_package_template/__init__.py
mcl_python_package_template/__main__.py
mcl_python_package_template/config.py
mcl_python_package_template/greetings.py
mcl_python_package_template/logging.py
mcl_python_package_template-0.1.1.dist-info/LICENSE
mcl_python_package_template-0.1.1.dist-info/WHEEL
mcl_python_package_template-0.1.1.dist-info/METADATA
mcl_python_package_template-0.1.1.dist-info/RECORD
