Metadata-Version: 2.1
Name: mcl-python-package-template
Version: 0.1.1
Summary: The mcl_python_package_template package
License: MIT
Author: Manuel Castillo
Author-email: manucalop@gmail.com
Requires-Python: >=3.9,<4.0
Classifier: License :: OSI Approved :: MIT License
Classifier: Programming Language :: Python :: 3
Classifier: Programming Language :: Python :: 3.10
Classifier: Programming Language :: Python :: 3.9
